{
  "MatchData": {
    "match_description": "",
    "match_time": "15:15",
    "home_score": 2,
    "guest_score": 0,
    "match_id": 584,
    "match_date": "2006-03-26",
    "matchStatus": "完場",
    "match_attendance": 0,
    "match_status": 1,
    "venue_id": 25,
    "live_icon": [],
    "home_shoot": null,
    "guest_shoot": null,
    "home_shoot_on_target": null,
    "guest_shoot_on_target": null,
    "home_corner": null,
    "guest_corner": null,
    "home_offside": null,
    "guest_offside": null,
    "home_fouls": null,
    "guest_fouls": null,
    "home_saves": null,
    "guest_saves": null,
    "home_12y_point": 0,
    "guest_12y_point": 0,
    "referee1": "",
    "referee2": "",
    "referee3": "",
    "referee4": "",
    "Venue": {
      "venue_id": 25,
      "VenueName": "深水埗運動場"
    },
    "LeagueYear": {
      "league_id": 2,
      "LeagueYearName": "乙組聯賽"
    },
    "team_home": {
      "Club": {
        "club_id": 16
      },
      "clublogo": "https://resource.hkfa.com/var/images/team_logo/kwaiching.png",
      "TeamName": "葵青"
    },
    "team_guest": {
      "Club": {
        "club_id": 11
      },
      "clublogo": "https://resource.hkfa.com/var/images/team/logo/div1/doubleflower2.png",
      "TeamName": "花花"
    },
    "HomePlayers": [
      {
        "Player": {
          "player_id": 4940,
          "PlayerName": "Benavides Gongora, Oscar Felix",
          "player_position": ""
        },
        "player_id": 4940,
        "captain": false,
        "leagueyearteamplayer_id": 399,
        "leagueyearteam_id": 12,
        "clubplayer_id": null,
        "player_jersey": null
      },
      {
        "Player": {
          "player_id": 5486,
          "PlayerName": "鄭偉揚",
          "player_position": null
        },
        "player_id": 5486,
        "captain": false,
        "leagueyearteamplayer_id": 4044,
        "leagueyearteam_id": 12,
        "clubplayer_id": null,
        "player_jersey": null
      },
      {
        "Player": {
          "player_id": 4866,
          "PlayerName": "李思豪",
          "player_position": ""
        },
        "player_id": 4866,
        "captain": false,
        "leagueyearteamplayer_id": 378,
        "leagueyearteam_id": 12,
        "clubplayer_id": null,
        "player_jersey": null
      },
      {
        "Player": {
          "player_id": 5491,
          "PlayerName": "梁嘉佑",
          "player_position": null
        },
        "player_id": 5491,
        "captain": false,
        "leagueyearteamplayer_id": 4039,
        "leagueyearteam_id": 12,
        "clubplayer_id": null,
        "player_jersey": null
      },
      {
        "Player": {
          "player_id": 4910,
          "PlayerName": "梁煒傑",
          "player_position": ""
        },
        "player_id": 4910,
        "captain": false,
        "leagueyearteamplayer_id": 397,
        "leagueyearteam_id": 12,
        "clubplayer_id": null,
        "player_jersey": null
      },
      {
        "Player": {
          "player_id": 5445,
          "PlayerName": "李啟揚",
          "player_position": ""
        },
        "player_id": 5445,
        "captain": false,
        "leagueyearteamplayer_id": 3944,
        "leagueyearteam_id": 12,
        "clubplayer_id": null,
        "player_jersey": null
      },
      {
        "Player": {
          "player_id": 4876,
          "PlayerName": "羅鈞耀",
          "player_position": ""
        },
        "player_id": 4876,
        "captain": false,
        "leagueyearteamplayer_id": 388,
        "leagueyearteam_id": 12,
        "clubplayer_id": null,
        "player_jersey": null
      },
      {
        "Player": {
          "player_id": 4909,
          "PlayerName": "彭耀慈",
          "player_position": ""
        },
        "player_id": 4909,
        "captain": true,
        "leagueyearteamplayer_id": 395,
        "leagueyearteam_id": 12,
        "clubplayer_id": null,
        "player_jersey": null
      },
      {
        "Player": {
          "player_id": 5446,
          "PlayerName": "鄧添識",
          "player_position": null
        },
        "player_id": 5446,
        "captain": false,
        "leagueyearteamplayer_id": 3943,
        "leagueyearteam_id": 12,
        "clubplayer_id": null,
        "player_jersey": null
      },
      {
        "Player": {
          "player_id": 4867,
          "PlayerName": "鄧冠研",
          "player_position": ""
        },
        "player_id": 4867,
        "captain": false,
        "leagueyearteamplayer_id": 379,
        "leagueyearteam_id": 12,
        "clubplayer_id": null,
        "player_jersey": null
      },
      {
        "Player": {
          "player_id": 5484,
          "PlayerName": "黃學炫",
          "player_position": null
        },
        "player_id": 5484,
        "captain": false,
        "leagueyearteamplayer_id": 3989,
        "leagueyearteam_id": 12,
        "clubplayer_id": null,
        "player_jersey": null
      }
    ],
    "HomeSubPlayers": [
      {
        "Player": {
          "player_id": 5493,
          "PlayerName": "鄭詠基",
          "player_position": null
        },
        "player_id": 5493,
        "captain": false,
        "leagueyearteamplayer_id": 4041,
        "leagueyearteam_id": 12,
        "clubplayer_id": null,
        "player_jersey": null
      },
      {
        "Player": {
          "player_id": 5448,
          "PlayerName": "霍偉倫",
          "player_position": null
        },
        "player_id": 5448,
        "captain": false,
        "leagueyearteamplayer_id": 3941,
        "leagueyearteam_id": 12,
        "clubplayer_id": null,
        "player_jersey": null
      },
      {
        "Player": {
          "player_id": 4864,
          "PlayerName": "黎俊彥",
          "player_position": ""
        },
        "player_id": 4864,
        "captain": false,
        "leagueyearteamplayer_id": 376,
        "leagueyearteam_id": 12,
        "clubplayer_id": null,
        "player_jersey": null
      },
      {
        "Player": {
          "player_id": 5488,
          "PlayerName": "林建榮",
          "player_position": ""
        },
        "player_id": 5488,
        "captain": false,
        "leagueyearteamplayer_id": 3992,
        "leagueyearteam_id": 12,
        "clubplayer_id": null,
        "player_jersey": null
      },
      {
        "Player": {
          "player_id": 5494,
          "PlayerName": "戴高喬",
          "player_position": ""
        },
        "player_id": 5494,
        "captain": false,
        "leagueyearteamplayer_id": 4042,
        "leagueyearteam_id": 12,
        "clubplayer_id": null,
        "player_jersey": null
      },
      {
        "Player": {
          "player_id": 5449,
          "PlayerName": "黃正光",
          "player_position": null
        },
        "player_id": 5449,
        "captain": false,
        "leagueyearteamplayer_id": 3940,
        "leagueyearteam_id": 12,
        "clubplayer_id": null,
        "player_jersey": null
      },
      {
        "Player": {
          "player_id": 4865,
          "PlayerName": "余小資",
          "player_position": ""
        },
        "player_id": 4865,
        "captain": false,
        "leagueyearteamplayer_id": 377,
        "leagueyearteam_id": 12,
        "clubplayer_id": null,
        "player_jersey": null
      }
    ],
    "GuestPlayers": [
      {
        "Player": {
          "player_id": 3752,
          "PlayerName": "陳子傑",
          "player_position": ""
        },
        "player_id": 3752,
        "captain": false,
        "leagueyearteamplayer_id": 260,
        "leagueyearteam_id": 11,
        "clubplayer_id": null,
        "player_jersey": null
      },
      {
        "Player": {
          "player_id": 3761,
          "PlayerName": "陳志賢",
          "player_position": null
        },
        "player_id": 3761,
        "captain": false,
        "leagueyearteamplayer_id": 270,
        "leagueyearteam_id": 11,
        "clubplayer_id": null,
        "player_jersey": null
      },
      {
        "Player": {
          "player_id": 3751,
          "PlayerName": "陳海彰",
          "player_position": ""
        },
        "player_id": 3751,
        "captain": false,
        "leagueyearteamplayer_id": 258,
        "leagueyearteam_id": 11,
        "clubplayer_id": null,
        "player_jersey": null
      },
      {
        "Player": {
          "player_id": 3747,
          "PlayerName": "張昊明",
          "player_position": ""
        },
        "player_id": 3747,
        "captain": false,
        "leagueyearteamplayer_id": 254,
        "leagueyearteam_id": 11,
        "clubplayer_id": null,
        "player_jersey": "0"
      },
      {
        "Player": {
          "player_id": 3750,
          "PlayerName": "趙俊文",
          "player_position": ""
        },
        "player_id": 3750,
        "captain": true,
        "leagueyearteamplayer_id": 257,
        "leagueyearteam_id": 11,
        "clubplayer_id": null,
        "player_jersey": null
      },
      {
        "Player": {
          "player_id": 3763,
          "PlayerName": "高騰芳",
          "player_position": ""
        },
        "player_id": 3763,
        "captain": false,
        "leagueyearteamplayer_id": 272,
        "leagueyearteam_id": 11,
        "clubplayer_id": null,
        "player_jersey": null
      },
      {
        "Player": {
          "player_id": 3757,
          "PlayerName": "黎震豪",
          "player_position": ""
        },
        "player_id": 3757,
        "captain": false,
        "leagueyearteamplayer_id": 265,
        "leagueyearteam_id": 11,
        "clubplayer_id": null,
        "player_jersey": null
      },
      {
        "Player": {
          "player_id": 3762,
          "PlayerName": "李騰駿",
          "player_position": ""
        },
        "player_id": 3762,
        "captain": false,
        "leagueyearteamplayer_id": 271,
        "leagueyearteam_id": 11,
        "clubplayer_id": null,
        "player_jersey": null
      },
      {
        "Player": {
          "player_id": 3749,
          "PlayerName": "李永恒",
          "player_position": ""
        },
        "player_id": 3749,
        "captain": false,
        "leagueyearteamplayer_id": 256,
        "leagueyearteam_id": 11,
        "clubplayer_id": null,
        "player_jersey": "0"
      },
      {
        "Player": {
          "player_id": 3759,
          "PlayerName": "文劍虹",
          "player_position": ""
        },
        "player_id": 3759,
        "captain": false,
        "leagueyearteamplayer_id": 267,
        "leagueyearteam_id": 11,
        "clubplayer_id": null,
        "player_jersey": null
      },
      {
        "Player": {
          "player_id": 4853,
          "PlayerName": "潘俊偉",
          "player_position": ""
        },
        "player_id": 4853,
        "captain": false,
        "leagueyearteamplayer_id": 274,
        "leagueyearteam_id": 11,
        "clubplayer_id": null,
        "player_jersey": null
      }
    ],
    "GuestSubPlayers": [
      {
        "Player": {
          "player_id": 3753,
          "PlayerName": "陳文俊",
          "player_position": ""
        },
        "player_id": 3753,
        "captain": false,
        "leagueyearteamplayer_id": 261,
        "leagueyearteam_id": 11,
        "clubplayer_id": null,
        "player_jersey": null
      },
      {
        "Player": {
          "player_id": 5476,
          "PlayerName": "張東成",
          "player_position": ""
        },
        "player_id": 5476,
        "captain": false,
        "leagueyearteamplayer_id": 3982,
        "leagueyearteam_id": 11,
        "clubplayer_id": null,
        "player_jersey": null
      },
      {
        "Player": {
          "player_id": 3746,
          "PlayerName": "何錦培",
          "player_position": ""
        },
        "player_id": 3746,
        "captain": false,
        "leagueyearteamplayer_id": 253,
        "leagueyearteam_id": 11,
        "clubplayer_id": null,
        "player_jersey": null
      },
      {
        "Player": {
          "player_id": 3755,
          "PlayerName": "林志昊",
          "player_position": ""
        },
        "player_id": 3755,
        "captain": false,
        "leagueyearteamplayer_id": 263,
        "leagueyearteam_id": 11,
        "clubplayer_id": null,
        "player_jersey": null
      },
      {
        "Player": {
          "player_id": 3748,
          "PlayerName": "梁志龍",
          "player_position": ""
        },
        "player_id": 3748,
        "captain": false,
        "leagueyearteamplayer_id": 255,
        "leagueyearteam_id": 11,
        "clubplayer_id": null,
        "player_jersey": null
      },
      {
        "Player": {
          "player_id": 3754,
          "PlayerName": "盧鴻鍵",
          "player_position": ""
        },
        "player_id": 3754,
        "captain": false,
        "leagueyearteamplayer_id": 262,
        "leagueyearteam_id": 11,
        "clubplayer_id": null,
        "player_jersey": null
      }
    ],
    "MatchEvents": [
      {
        "teamplayer_home_id": 395,
        "teamplayer_home_sub_id": 0,
        "teamplayer_guest_id": 0,
        "teamplayer_guest_sub_id": 0,
        "teamplayer_home": {
          "player_id": 4909,
          "club_id": 0,
          "PlayerName": "彭耀慈",
          "player_position": ""
        },
        "teamplayer_home_sub": null,
        "teamplayer_guest": null,
        "teamplayer_guest_sub": null,
        "EventType": "G",
        "side": "Home",
        "min": 76,
        "minExtra": 0,
        "EXCPlayer": null
      },
      {
        "teamplayer_home_id": 3944,
        "teamplayer_home_sub_id": 0,
        "teamplayer_guest_id": 0,
        "teamplayer_guest_sub_id": 0,
        "teamplayer_home": {
          "player_id": 5445,
          "club_id": 0,
          "PlayerName": "李啟揚",
          "player_position": ""
        },
        "teamplayer_home_sub": null,
        "teamplayer_guest": null,
        "teamplayer_guest_sub": null,
        "EventType": "G",
        "side": "Home",
        "min": 89,
        "minExtra": 0,
        "EXCPlayer": null
      },
      {
        "teamplayer_home_id": 0,
        "teamplayer_home_sub_id": 0,
        "teamplayer_guest_id": 260,
        "teamplayer_guest_sub_id": 0,
        "teamplayer_home": null,
        "teamplayer_home_sub": null,
        "teamplayer_guest": {
          "player_id": 3752,
          "club_id": 0,
          "PlayerName": "陳子傑",
          "player_position": ""
        },
        "teamplayer_guest_sub": null,
        "EventType": "YC",
        "side": "Guest",
        "min": 54,
        "minExtra": 0,
        "EXCPlayer": null
      },
      {
        "teamplayer_home_id": 4042,
        "teamplayer_home_sub_id": 397,
        "teamplayer_guest_id": 0,
        "teamplayer_guest_sub_id": 0,
        "teamplayer_home": {
          "player_id": 5494,
          "club_id": 0,
          "PlayerName": "戴高喬",
          "player_position": ""
        },
        "teamplayer_home_sub": {
          "player_id": 4910,
          "club_id": 0,
          "PlayerName": "梁煒傑",
          "player_position": ""
        },
        "teamplayer_guest": null,
        "teamplayer_guest_sub": null,
        "EventType": "EXC",
        "side": "Home",
        "min": 46,
        "minExtra": 0,
        "EXCPlayer": {
          "side": "Home",
          "from": {
            "Player": {
              "PlayerName": "戴高喬",
              "player_position": ""
            },
            "player_id": 5494,
            "leagueyearteamplayer_id": 4042,
            "leagueyearteam_id": 12,
            "clubplayer_id": null,
            "player_jersey": null
          },
          "to": {
            "Player": {
              "PlayerName": "梁煒傑",
              "player_position": ""
            },
            "player_id": 4910,
            "leagueyearteamplayer_id": 397,
            "leagueyearteam_id": 12,
            "clubplayer_id": null,
            "player_jersey": null
          }
        }
      },
      {
        "teamplayer_home_id": 0,
        "teamplayer_home_sub_id": 0,
        "teamplayer_guest_id": 262,
        "teamplayer_guest_sub_id": 271,
        "teamplayer_home": null,
        "teamplayer_home_sub": null,
        "teamplayer_guest": {
          "player_id": 3754,
          "club_id": 0,
          "PlayerName": "盧鴻鍵",
          "player_position": ""
        },
        "teamplayer_guest_sub": {
          "player_id": 3762,
          "club_id": 0,
          "PlayerName": "李騰駿",
          "player_position": ""
        },
        "EventType": "EXC",
        "side": "Guest",
        "min": 46,
        "minExtra": 0,
        "EXCPlayer": {
          "side": "Guest",
          "from": {
            "Player": {
              "PlayerName": "盧鴻鍵",
              "player_position": ""
            },
            "player_id": 3754,
            "leagueyearteamplayer_id": 262,
            "leagueyearteam_id": 11,
            "clubplayer_id": null,
            "player_jersey": null
          },
          "to": {
            "Player": {
              "PlayerName": "李騰駿",
              "player_position": ""
            },
            "player_id": 3762,
            "leagueyearteamplayer_id": 271,
            "leagueyearteam_id": 11,
            "clubplayer_id": null,
            "player_jersey": null
          }
        }
      },
      {
        "teamplayer_home_id": 3992,
        "teamplayer_home_sub_id": 399,
        "teamplayer_guest_id": 0,
        "teamplayer_guest_sub_id": 0,
        "teamplayer_home": {
          "player_id": 5488,
          "club_id": 0,
          "PlayerName": "林建榮",
          "player_position": ""
        },
        "teamplayer_home_sub": {
          "player_id": 4940,
          "club_id": 0,
          "PlayerName": "Benavides Gongora, Oscar Felix",
          "player_position": ""
        },
        "teamplayer_guest": null,
        "teamplayer_guest_sub": null,
        "EventType": "EXC",
        "side": "Home",
        "min": 53,
        "minExtra": 0,
        "EXCPlayer": {
          "side": "Home",
          "from": {
            "Player": {
              "PlayerName": "林建榮",
              "player_position": ""
            },
            "player_id": 5488,
            "leagueyearteamplayer_id": 3992,
            "leagueyearteam_id": 12,
            "clubplayer_id": null,
            "player_jersey": null
          },
          "to": {
            "Player": {
              "PlayerName": "Benavides Gongora, Oscar Felix",
              "player_position": ""
            },
            "player_id": 4940,
            "leagueyearteamplayer_id": 399,
            "leagueyearteam_id": 12,
            "clubplayer_id": null,
            "player_jersey": null
          }
        }
      },
      {
        "teamplayer_home_id": 0,
        "teamplayer_home_sub_id": 0,
        "teamplayer_guest_id": 263,
        "teamplayer_guest_sub_id": 270,
        "teamplayer_home": null,
        "teamplayer_home_sub": null,
        "teamplayer_guest": {
          "player_id": 3755,
          "club_id": 0,
          "PlayerName": "林志昊",
          "player_position": ""
        },
        "teamplayer_guest_sub": {
          "player_id": 3761,
          "club_id": 0,
          "PlayerName": "陳志賢",
          "player_position": null
        },
        "EventType": "EXC",
        "side": "Guest",
        "min": 63,
        "minExtra": 0,
        "EXCPlayer": {
          "side": "Guest",
          "from": {
            "Player": {
              "PlayerName": "林志昊",
              "player_position": ""
            },
            "player_id": 3755,
            "leagueyearteamplayer_id": 263,
            "leagueyearteam_id": 11,
            "clubplayer_id": null,
            "player_jersey": null
          },
          "to": {
            "Player": {
              "PlayerName": "陳志賢",
              "player_position": null
            },
            "player_id": 3761,
            "leagueyearteamplayer_id": 270,
            "leagueyearteam_id": 11,
            "clubplayer_id": null,
            "player_jersey": null
          }
        }
      },
      {
        "teamplayer_home_id": 3940,
        "teamplayer_home_sub_id": 388,
        "teamplayer_guest_id": 0,
        "teamplayer_guest_sub_id": 0,
        "teamplayer_home": {
          "player_id": 5449,
          "club_id": 0,
          "PlayerName": "黃正光",
          "player_position": null
        },
        "teamplayer_home_sub": {
          "player_id": 4876,
          "club_id": 0,
          "PlayerName": "羅鈞耀",
          "player_position": ""
        },
        "teamplayer_guest": null,
        "teamplayer_guest_sub": null,
        "EventType": "EXC",
        "side": "Home",
        "min": 72,
        "minExtra": 0,
        "EXCPlayer": {
          "side": "Home",
          "from": {
            "Player": {
              "PlayerName": "黃正光",
              "player_position": null
            },
            "player_id": 5449,
            "leagueyearteamplayer_id": 3940,
            "leagueyearteam_id": 12,
            "clubplayer_id": null,
            "player_jersey": null
          },
          "to": {
            "Player": {
              "PlayerName": "羅鈞耀",
              "player_position": ""
            },
            "player_id": 4876,
            "leagueyearteamplayer_id": 388,
            "leagueyearteam_id": 12,
            "clubplayer_id": null,
            "player_jersey": null
          }
        }
      }
    ],
    "report": {
      "news_id": null,
      "news_date": null,
      "news_title": null,
      "news_abstract": null,
      "news_content": null,
      "news_image_1": null,
      "news_image_2": null,
      "news_image_3": null,
      "news_image_4": null,
      "news_image_5": null,
      "news_image_6": null,
      "news_league": null,
      "news_hkteam_type": null
    }
  },
  "HomePlayersTable": [
    {
      "Player": {
        "player_id": 4940,
        "PlayerName": "Benavides Gongora, Oscar Felix",
        "player_position": ""
      },
      "player_id": 4940,
      "captain": false,
      "leagueyearteamplayer_id": 399,
      "leagueyearteam_id": 12,
      "clubplayer_id": null,
      "player_jersey": null
    },
    {
      "Player": {
        "player_id": 5486,
        "PlayerName": "鄭偉揚",
        "player_position": null
      },
      "player_id": 5486,
      "captain": false,
      "leagueyearteamplayer_id": 4044,
      "leagueyearteam_id": 12,
      "clubplayer_id": null,
      "player_jersey": null
    },
    {
      "Player": {
        "player_id": 4866,
        "PlayerName": "李思豪",
        "player_position": ""
      },
      "player_id": 4866,
      "captain": false,
      "leagueyearteamplayer_id": 378,
      "leagueyearteam_id": 12,
      "clubplayer_id": null,
      "player_jersey": null
    },
    {
      "Player": {
        "player_id": 5491,
        "PlayerName": "梁嘉佑",
        "player_position": null
      },
      "player_id": 5491,
      "captain": false,
      "leagueyearteamplayer_id": 4039,
      "leagueyearteam_id": 12,
      "clubplayer_id": null,
      "player_jersey": null
    },
    {
      "Player": {
        "player_id": 4910,
        "PlayerName": "梁煒傑",
        "player_position": ""
      },
      "player_id": 4910,
      "captain": false,
      "leagueyearteamplayer_id": 397,
      "leagueyearteam_id": 12,
      "clubplayer_id": null,
      "player_jersey": null
    },
    {
      "Player": {
        "player_id": 5445,
        "PlayerName": "李啟揚",
        "player_position": ""
      },
      "player_id": 5445,
      "captain": false,
      "leagueyearteamplayer_id": 3944,
      "leagueyearteam_id": 12,
      "clubplayer_id": null,
      "player_jersey": null
    },
    {
      "Player": {
        "player_id": 4876,
        "PlayerName": "羅鈞耀",
        "player_position": ""
      },
      "player_id": 4876,
      "captain": false,
      "leagueyearteamplayer_id": 388,
      "leagueyearteam_id": 12,
      "clubplayer_id": null,
      "player_jersey": null
    },
    {
      "Player": {
        "player_id": 4909,
        "PlayerName": "彭耀慈",
        "player_position": ""
      },
      "player_id": 4909,
      "captain": true,
      "leagueyearteamplayer_id": 395,
      "leagueyearteam_id": 12,
      "clubplayer_id": null,
      "player_jersey": null
    },
    {
      "Player": {
        "player_id": 5446,
        "PlayerName": "鄧添識",
        "player_position": null
      },
      "player_id": 5446,
      "captain": false,
      "leagueyearteamplayer_id": 3943,
      "leagueyearteam_id": 12,
      "clubplayer_id": null,
      "player_jersey": null
    },
    {
      "Player": {
        "player_id": 4867,
        "PlayerName": "鄧冠研",
        "player_position": ""
      },
      "player_id": 4867,
      "captain": false,
      "leagueyearteamplayer_id": 379,
      "leagueyearteam_id": 12,
      "clubplayer_id": null,
      "player_jersey": null
    },
    {
      "Player": {
        "player_id": 5484,
        "PlayerName": "黃學炫",
        "player_position": null
      },
      "player_id": 5484,
      "captain": false,
      "leagueyearteamplayer_id": 3989,
      "leagueyearteam_id": 12,
      "clubplayer_id": null,
      "player_jersey": null
    }
  ],
  "GuestPlayersTable": [
    {
      "Player": {
        "player_id": 3752,
        "PlayerName": "陳子傑",
        "player_position": ""
      },
      "player_id": 3752,
      "captain": false,
      "leagueyearteamplayer_id": 260,
      "leagueyearteam_id": 11,
      "clubplayer_id": null,
      "player_jersey": null
    },
    {
      "Player": {
        "player_id": 3761,
        "PlayerName": "陳志賢",
        "player_position": null
      },
      "player_id": 3761,
      "captain": false,
      "leagueyearteamplayer_id": 270,
      "leagueyearteam_id": 11,
      "clubplayer_id": null,
      "player_jersey": null
    },
    {
      "Player": {
        "player_id": 3751,
        "PlayerName": "陳海彰",
        "player_position": ""
      },
      "player_id": 3751,
      "captain": false,
      "leagueyearteamplayer_id": 258,
      "leagueyearteam_id": 11,
      "clubplayer_id": null,
      "player_jersey": null
    },
    {
      "Player": {
        "player_id": 3747,
        "PlayerName": "張昊明",
        "player_position": ""
      },
      "player_id": 3747,
      "captain": false,
      "leagueyearteamplayer_id": 254,
      "leagueyearteam_id": 11,
      "clubplayer_id": null,
      "player_jersey": "0"
    },
    {
      "Player": {
        "player_id": 3750,
        "PlayerName": "趙俊文",
        "player_position": ""
      },
      "player_id": 3750,
      "captain": true,
      "leagueyearteamplayer_id": 257,
      "leagueyearteam_id": 11,
      "clubplayer_id": null,
      "player_jersey": null
    },
    {
      "Player": {
        "player_id": 3763,
        "PlayerName": "高騰芳",
        "player_position": ""
      },
      "player_id": 3763,
      "captain": false,
      "leagueyearteamplayer_id": 272,
      "leagueyearteam_id": 11,
      "clubplayer_id": null,
      "player_jersey": null
    },
    {
      "Player": {
        "player_id": 3757,
        "PlayerName": "黎震豪",
        "player_position": ""
      },
      "player_id": 3757,
      "captain": false,
      "leagueyearteamplayer_id": 265,
      "leagueyearteam_id": 11,
      "clubplayer_id": null,
      "player_jersey": null
    },
    {
      "Player": {
        "player_id": 3762,
        "PlayerName": "李騰駿",
        "player_position": ""
      },
      "player_id": 3762,
      "captain": false,
      "leagueyearteamplayer_id": 271,
      "leagueyearteam_id": 11,
      "clubplayer_id": null,
      "player_jersey": null
    },
    {
      "Player": {
        "player_id": 3749,
        "PlayerName": "李永恒",
        "player_position": ""
      },
      "player_id": 3749,
      "captain": false,
      "leagueyearteamplayer_id": 256,
      "leagueyearteam_id": 11,
      "clubplayer_id": null,
      "player_jersey": "0"
    },
    {
      "Player": {
        "player_id": 3759,
        "PlayerName": "文劍虹",
        "player_position": ""
      },
      "player_id": 3759,
      "captain": false,
      "leagueyearteamplayer_id": 267,
      "leagueyearteam_id": 11,
      "clubplayer_id": null,
      "player_jersey": null
    },
    {
      "Player": {
        "player_id": 4853,
        "PlayerName": "潘俊偉",
        "player_position": ""
      },
      "player_id": 4853,
      "captain": false,
      "leagueyearteamplayer_id": 274,
      "leagueyearteam_id": 11,
      "clubplayer_id": null,
      "player_jersey": null
    }
  ],
  "HomeSubPlayersTable": [
    {
      "Player": {
        "player_id": 5493,
        "PlayerName": "鄭詠基",
        "player_position": null
      },
      "player_id": 5493,
      "captain": false,
      "leagueyearteamplayer_id": 4041,
      "leagueyearteam_id": 12,
      "clubplayer_id": null,
      "player_jersey": null
    },
    {
      "Player": {
        "player_id": 5448,
        "PlayerName": "霍偉倫",
        "player_position": null
      },
      "player_id": 5448,
      "captain": false,
      "leagueyearteamplayer_id": 3941,
      "leagueyearteam_id": 12,
      "clubplayer_id": null,
      "player_jersey": null
    },
    {
      "Player": {
        "player_id": 4864,
        "PlayerName": "黎俊彥",
        "player_position": ""
      },
      "player_id": 4864,
      "captain": false,
      "leagueyearteamplayer_id": 376,
      "leagueyearteam_id": 12,
      "clubplayer_id": null,
      "player_jersey": null
    },
    {
      "Player": {
        "player_id": 5488,
        "PlayerName": "林建榮",
        "player_position": ""
      },
      "player_id": 5488,
      "captain": false,
      "leagueyearteamplayer_id": 3992,
      "leagueyearteam_id": 12,
      "clubplayer_id": null,
      "player_jersey": null
    },
    {
      "Player": {
        "player_id": 5494,
        "PlayerName": "戴高喬",
        "player_position": ""
      },
      "player_id": 5494,
      "captain": false,
      "leagueyearteamplayer_id": 4042,
      "leagueyearteam_id": 12,
      "clubplayer_id": null,
      "player_jersey": null
    },
    {
      "Player": {
        "player_id": 5449,
        "PlayerName": "黃正光",
        "player_position": null
      },
      "player_id": 5449,
      "captain": false,
      "leagueyearteamplayer_id": 3940,
      "leagueyearteam_id": 12,
      "clubplayer_id": null,
      "player_jersey": null
    },
    {
      "Player": {
        "player_id": 4865,
        "PlayerName": "余小資",
        "player_position": ""
      },
      "player_id": 4865,
      "captain": false,
      "leagueyearteamplayer_id": 377,
      "leagueyearteam_id": 12,
      "clubplayer_id": null,
      "player_jersey": null
    }
  ],
  "GuestSubPlayersTable": [
    {
      "Player": {
        "player_id": 3753,
        "PlayerName": "陳文俊",
        "player_position": ""
      },
      "player_id": 3753,
      "captain": false,
      "leagueyearteamplayer_id": 261,
      "leagueyearteam_id": 11,
      "clubplayer_id": null,
      "player_jersey": null
    },
    {
      "Player": {
        "player_id": 5476,
        "PlayerName": "張東成",
        "player_position": ""
      },
      "player_id": 5476,
      "captain": false,
      "leagueyearteamplayer_id": 3982,
      "leagueyearteam_id": 11,
      "clubplayer_id": null,
      "player_jersey": null
    },
    {
      "Player": {
        "player_id": 3746,
        "PlayerName": "何錦培",
        "player_position": ""
      },
      "player_id": 3746,
      "captain": false,
      "leagueyearteamplayer_id": 253,
      "leagueyearteam_id": 11,
      "clubplayer_id": null,
      "player_jersey": null
    },
    {
      "Player": {
        "player_id": 3755,
        "PlayerName": "林志昊",
        "player_position": ""
      },
      "player_id": 3755,
      "captain": false,
      "leagueyearteamplayer_id": 263,
      "leagueyearteam_id": 11,
      "clubplayer_id": null,
      "player_jersey": null
    },
    {
      "Player": {
        "player_id": 3748,
        "PlayerName": "梁志龍",
        "player_position": ""
      },
      "player_id": 3748,
      "captain": false,
      "leagueyearteamplayer_id": 255,
      "leagueyearteam_id": 11,
      "clubplayer_id": null,
      "player_jersey": null
    },
    {
      "Player": {
        "player_id": 3754,
        "PlayerName": "盧鴻鍵",
        "player_position": ""
      },
      "player_id": 3754,
      "captain": false,
      "leagueyearteamplayer_id": 262,
      "leagueyearteam_id": 11,
      "clubplayer_id": null,
      "player_jersey": null
    }
  ],
  "HomeStatisticTable": {
    "shoot": null,
    "shoot_on_target": null,
    "corner": null,
    "offside": null,
    "fouls": null,
    "saves": null,
    "yc": 0,
    "rc": 0
  },
  "GuestStatisticTable": {
    "shoot": null,
    "shoot_on_target": null,
    "corner": null,
    "offside": null,
    "fouls": null,
    "saves": null,
    "yc": 1,
    "rc": 0
  },
  "HomeGoalPlayerTable": [
    {
      "teamplayer_home_id": 395,
      "teamplayer_home_sub_id": 0,
      "teamplayer_guest_id": 0,
      "teamplayer_guest_sub_id": 0,
      "teamplayer_home": {
        "player_id": 4909,
        "club_id": 0,
        "PlayerName": "彭耀慈",
        "player_position": ""
      },
      "teamplayer_home_sub": null,
      "teamplayer_guest": null,
      "teamplayer_guest_sub": null,
      "EventType": "G",
      "side": "Home",
      "min": 76,
      "minExtra": 0,
      "EXCPlayer": null
    },
    {
      "teamplayer_home_id": 3944,
      "teamplayer_home_sub_id": 0,
      "teamplayer_guest_id": 0,
      "teamplayer_guest_sub_id": 0,
      "teamplayer_home": {
        "player_id": 5445,
        "club_id": 0,
        "PlayerName": "李啟揚",
        "player_position": ""
      },
      "teamplayer_home_sub": null,
      "teamplayer_guest": null,
      "teamplayer_guest_sub": null,
      "EventType": "G",
      "side": "Home",
      "min": 89,
      "minExtra": 0,
      "EXCPlayer": null
    }
  ],
  "GuestGoalPlayerTable": [],
  "Home12YPlayerTable": [],
  "Guest12YPlayerTable": [],
  "HomeYCTable": [],
  "GuestYCTable": [
    {
      "teamplayer_home_id": 0,
      "teamplayer_home_sub_id": 0,
      "teamplayer_guest_id": 260,
      "teamplayer_guest_sub_id": 0,
      "teamplayer_home": null,
      "teamplayer_home_sub": null,
      "teamplayer_guest": {
        "player_id": 3752,
        "club_id": 0,
        "PlayerName": "陳子傑",
        "player_position": ""
      },
      "teamplayer_guest_sub": null,
      "EventType": "YC",
      "side": "Guest",
      "min": 54,
      "minExtra": 0,
      "EXCPlayer": null
    }
  ],
  "HomeRCTable": [],
  "GuestRCTable": [],
  "HomeEXCTable": [
    {
      "teamplayer_home_id": 4042,
      "teamplayer_home_sub_id": 397,
      "teamplayer_guest_id": 0,
      "teamplayer_guest_sub_id": 0,
      "teamplayer_home": {
        "player_id": 5494,
        "club_id": 0,
        "PlayerName": "戴高喬",
        "player_position": ""
      },
      "teamplayer_home_sub": {
        "player_id": 4910,
        "club_id": 0,
        "PlayerName": "梁煒傑",
        "player_position": ""
      },
      "teamplayer_guest": null,
      "teamplayer_guest_sub": null,
      "EventType": "EXC",
      "side": "Home",
      "min": 46,
      "minExtra": 0,
      "EXCPlayer": {
        "side": "Home",
        "from": {
          "Player": {
            "PlayerName": "戴高喬",
            "player_position": ""
          },
          "player_id": 5494,
          "leagueyearteamplayer_id": 4042,
          "leagueyearteam_id": 12,
          "clubplayer_id": null,
          "player_jersey": null
        },
        "to": {
          "Player": {
            "PlayerName": "梁煒傑",
            "player_position": ""
          },
          "player_id": 4910,
          "leagueyearteamplayer_id": 397,
          "leagueyearteam_id": 12,
          "clubplayer_id": null,
          "player_jersey": null
        }
      }
    },
    {
      "teamplayer_home_id": 3992,
      "teamplayer_home_sub_id": 399,
      "teamplayer_guest_id": 0,
      "teamplayer_guest_sub_id": 0,
      "teamplayer_home": {
        "player_id": 5488,
        "club_id": 0,
        "PlayerName": "林建榮",
        "player_position": ""
      },
      "teamplayer_home_sub": {
        "player_id": 4940,
        "club_id": 0,
        "PlayerName": "Benavides Gongora, Oscar Felix",
        "player_position": ""
      },
      "teamplayer_guest": null,
      "teamplayer_guest_sub": null,
      "EventType": "EXC",
      "side": "Home",
      "min": 53,
      "minExtra": 0,
      "EXCPlayer": {
        "side": "Home",
        "from": {
          "Player": {
            "PlayerName": "林建榮",
            "player_position": ""
          },
          "player_id": 5488,
          "leagueyearteamplayer_id": 3992,
          "leagueyearteam_id": 12,
          "clubplayer_id": null,
          "player_jersey": null
        },
        "to": {
          "Player": {
            "PlayerName": "Benavides Gongora, Oscar Felix",
            "player_position": ""
          },
          "player_id": 4940,
          "leagueyearteamplayer_id": 399,
          "leagueyearteam_id": 12,
          "clubplayer_id": null,
          "player_jersey": null
        }
      }
    },
    {
      "teamplayer_home_id": 3940,
      "teamplayer_home_sub_id": 388,
      "teamplayer_guest_id": 0,
      "teamplayer_guest_sub_id": 0,
      "teamplayer_home": {
        "player_id": 5449,
        "club_id": 0,
        "PlayerName": "黃正光",
        "player_position": null
      },
      "teamplayer_home_sub": {
        "player_id": 4876,
        "club_id": 0,
        "PlayerName": "羅鈞耀",
        "player_position": ""
      },
      "teamplayer_guest": null,
      "teamplayer_guest_sub": null,
      "EventType": "EXC",
      "side": "Home",
      "min": 72,
      "minExtra": 0,
      "EXCPlayer": {
        "side": "Home",
        "from": {
          "Player": {
            "PlayerName": "黃正光",
            "player_position": null
          },
          "player_id": 5449,
          "leagueyearteamplayer_id": 3940,
          "leagueyearteam_id": 12,
          "clubplayer_id": null,
          "player_jersey": null
        },
        "to": {
          "Player": {
            "PlayerName": "羅鈞耀",
            "player_position": ""
          },
          "player_id": 4876,
          "leagueyearteamplayer_id": 388,
          "leagueyearteam_id": 12,
          "clubplayer_id": null,
          "player_jersey": null
        }
      }
    }
  ],
  "GuestEXCTable": [
    {
      "teamplayer_home_id": 0,
      "teamplayer_home_sub_id": 0,
      "teamplayer_guest_id": 262,
      "teamplayer_guest_sub_id": 271,
      "teamplayer_home": null,
      "teamplayer_home_sub": null,
      "teamplayer_guest": {
        "player_id": 3754,
        "club_id": 0,
        "PlayerName": "盧鴻鍵",
        "player_position": ""
      },
      "teamplayer_guest_sub": {
        "player_id": 3762,
        "club_id": 0,
        "PlayerName": "李騰駿",
        "player_position": ""
      },
      "EventType": "EXC",
      "side": "Guest",
      "min": 46,
      "minExtra": 0,
      "EXCPlayer": {
        "side": "Guest",
        "from": {
          "Player": {
            "PlayerName": "盧鴻鍵",
            "player_position": ""
          },
          "player_id": 3754,
          "leagueyearteamplayer_id": 262,
          "leagueyearteam_id": 11,
          "clubplayer_id": null,
          "player_jersey": null
        },
        "to": {
          "Player": {
            "PlayerName": "李騰駿",
            "player_position": ""
          },
          "player_id": 3762,
          "leagueyearteamplayer_id": 271,
          "leagueyearteam_id": 11,
          "clubplayer_id": null,
          "player_jersey": null
        }
      }
    },
    {
      "teamplayer_home_id": 0,
      "teamplayer_home_sub_id": 0,
      "teamplayer_guest_id": 263,
      "teamplayer_guest_sub_id": 270,
      "teamplayer_home": null,
      "teamplayer_home_sub": null,
      "teamplayer_guest": {
        "player_id": 3755,
        "club_id": 0,
        "PlayerName": "林志昊",
        "player_position": ""
      },
      "teamplayer_guest_sub": {
        "player_id": 3761,
        "club_id": 0,
        "PlayerName": "陳志賢",
        "player_position": null
      },
      "EventType": "EXC",
      "side": "Guest",
      "min": 63,
      "minExtra": 0,
      "EXCPlayer": {
        "side": "Guest",
        "from": {
          "Player": {
            "PlayerName": "林志昊",
            "player_position": ""
          },
          "player_id": 3755,
          "leagueyearteamplayer_id": 263,
          "leagueyearteam_id": 11,
          "clubplayer_id": null,
          "player_jersey": null
        },
        "to": {
          "Player": {
            "PlayerName": "陳志賢",
            "player_position": null
          },
          "player_id": 3761,
          "leagueyearteamplayer_id": 270,
          "leagueyearteam_id": 11,
          "clubplayer_id": null,
          "player_jersey": null
        }
      }
    }
  ]
}