{
  "MatchData": {
    "match_description": "",
    "match_time": "15:15",
    "home_score": 1,
    "guest_score": 1,
    "match_id": 967,
    "match_date": "2006-09-17",
    "matchStatus": "完場",
    "match_attendance": 0,
    "match_status": 1,
    "venue_id": 36,
    "live_icon": [],
    "home_shoot": null,
    "guest_shoot": null,
    "home_shoot_on_target": null,
    "guest_shoot_on_target": null,
    "home_corner": null,
    "guest_corner": null,
    "home_offside": null,
    "guest_offside": null,
    "home_fouls": null,
    "guest_fouls": null,
    "home_saves": null,
    "guest_saves": null,
    "home_12y_point": 0,
    "guest_12y_point": 0,
    "referee1": "",
    "referee2": "",
    "referee3": "",
    "referee4": "",
    "Venue": {
      "venue_id": 36,
      "VenueName": "粉嶺遊樂場"
    },
    "LeagueYear": {
      "league_id": 4,
      "LeagueYearName": "丙組\"地區\"聯賽"
    },
    "team_home": {
      "Club": {
        "club_id": 47
      },
      "clublogo": "https://resource.hkfa.com/var/images/team/logo/div3b/Golik_northern.png",
      "TeamName": "彩俊北區"
    },
    "team_guest": {
      "Club": {
        "club_id": 80
      },
      "clublogo": "https://resource.hkfa.com/var/images/team/logo/20122013/saikung.jpg",
      "TeamName": "西貢"
    },
    "HomePlayers": [
      {
        "Player": {
          "player_id": 6011,
          "PlayerName": "王偉成",
          "player_position": ""
        },
        "player_id": 6011,
        "captain": false,
        "leagueyearteamplayer_id": 7122,
        "leagueyearteam_id": 238,
        "clubplayer_id": null,
        "player_jersey": null
      },
      {
        "Player": {
          "player_id": 6019,
          "PlayerName": "周志豪",
          "player_position": ""
        },
        "player_id": 6019,
        "captain": false,
        "leagueyearteamplayer_id": 7138,
        "leagueyearteam_id": 238,
        "clubplayer_id": null,
        "player_jersey": null
      },
      {
        "Player": {
          "player_id": 4023,
          "PlayerName": "周劍鋒",
          "player_position": ""
        },
        "player_id": 4023,
        "captain": false,
        "leagueyearteamplayer_id": 7136,
        "leagueyearteam_id": 238,
        "clubplayer_id": null,
        "player_jersey": null
      },
      {
        "Player": {
          "player_id": 4020,
          "PlayerName": "何偉立",
          "player_position": ""
        },
        "player_id": 4020,
        "captain": true,
        "leagueyearteamplayer_id": 7143,
        "leagueyearteam_id": 238,
        "clubplayer_id": null,
        "player_jersey": "0"
      },
      {
        "Player": {
          "player_id": 4021,
          "PlayerName": "葉俊文",
          "player_position": ""
        },
        "player_id": 4021,
        "captain": false,
        "leagueyearteamplayer_id": 7126,
        "leagueyearteam_id": 238,
        "clubplayer_id": null,
        "player_jersey": null
      },
      {
        "Player": {
          "player_id": 4018,
          "PlayerName": "鄺禮健",
          "player_position": ""
        },
        "player_id": 4018,
        "captain": false,
        "leagueyearteamplayer_id": 7125,
        "leagueyearteam_id": 238,
        "clubplayer_id": null,
        "player_jersey": null
      },
      {
        "Player": {
          "player_id": 4816,
          "PlayerName": "駱旭文",
          "player_position": ""
        },
        "player_id": 4816,
        "captain": false,
        "leagueyearteamplayer_id": 7130,
        "leagueyearteam_id": 238,
        "clubplayer_id": null,
        "player_jersey": null
      },
      {
        "Player": {
          "player_id": 4028,
          "PlayerName": "吳志豪",
          "player_position": ""
        },
        "player_id": 4028,
        "captain": false,
        "leagueyearteamplayer_id": 7135,
        "leagueyearteam_id": 238,
        "clubplayer_id": null,
        "player_jersey": null
      },
      {
        "Player": {
          "player_id": 6017,
          "PlayerName": "潘兆恒",
          "player_position": ""
        },
        "player_id": 6017,
        "captain": false,
        "leagueyearteamplayer_id": 7145,
        "leagueyearteam_id": 238,
        "clubplayer_id": null,
        "player_jersey": null
      },
      {
        "Player": {
          "player_id": 6014,
          "PlayerName": "胡慶龍",
          "player_position": ""
        },
        "player_id": 6014,
        "captain": false,
        "leagueyearteamplayer_id": 7124,
        "leagueyearteam_id": 238,
        "clubplayer_id": null,
        "player_jersey": null
      },
      {
        "Player": {
          "player_id": 4032,
          "PlayerName": "阮國威",
          "player_position": ""
        },
        "player_id": 4032,
        "captain": false,
        "leagueyearteamplayer_id": 7128,
        "leagueyearteam_id": 238,
        "clubplayer_id": null,
        "player_jersey": null
      }
    ],
    "HomeSubPlayers": [
      {
        "Player": {
          "player_id": 4029,
          "PlayerName": "何偉健",
          "player_position": ""
        },
        "player_id": 4029,
        "captain": false,
        "leagueyearteamplayer_id": 7144,
        "leagueyearteam_id": 238,
        "clubplayer_id": null,
        "player_jersey": null
      },
      {
        "Player": {
          "player_id": 4817,
          "PlayerName": "賴志偉",
          "player_position": ""
        },
        "player_id": 4817,
        "captain": false,
        "leagueyearteamplayer_id": 7131,
        "leagueyearteam_id": 238,
        "clubplayer_id": null,
        "player_jersey": null
      },
      {
        "Player": {
          "player_id": 4938,
          "PlayerName": "黎振康",
          "player_position": ""
        },
        "player_id": 4938,
        "captain": false,
        "leagueyearteamplayer_id": 7133,
        "leagueyearteam_id": 238,
        "clubplayer_id": null,
        "player_jersey": null
      },
      {
        "Player": {
          "player_id": 6013,
          "PlayerName": "林肇璞",
          "player_position": ""
        },
        "player_id": 6013,
        "captain": false,
        "leagueyearteamplayer_id": 7141,
        "leagueyearteam_id": 238,
        "clubplayer_id": null,
        "player_jersey": null
      },
      {
        "Player": {
          "player_id": 4815,
          "PlayerName": "梁樂倫",
          "player_position": ""
        },
        "player_id": 4815,
        "captain": false,
        "leagueyearteamplayer_id": 7142,
        "leagueyearteam_id": 238,
        "clubplayer_id": null,
        "player_jersey": "0"
      },
      {
        "Player": {
          "player_id": 4026,
          "PlayerName": "李凱俊",
          "player_position": ""
        },
        "player_id": 4026,
        "captain": false,
        "leagueyearteamplayer_id": 7140,
        "leagueyearteam_id": 238,
        "clubplayer_id": null,
        "player_jersey": null
      },
      {
        "Player": {
          "player_id": 4034,
          "PlayerName": "黃牖良",
          "player_position": ""
        },
        "player_id": 4034,
        "captain": false,
        "leagueyearteamplayer_id": 7132,
        "leagueyearteam_id": 238,
        "clubplayer_id": null,
        "player_jersey": null
      }
    ],
    "GuestPlayers": [
      {
        "Player": {
          "player_id": 6027,
          "PlayerName": "郭志文",
          "player_position": ""
        },
        "player_id": 6027,
        "captain": false,
        "leagueyearteamplayer_id": 7147,
        "leagueyearteam_id": 239,
        "clubplayer_id": null,
        "player_jersey": null
      },
      {
        "Player": {
          "player_id": 6028,
          "PlayerName": "林浩賢",
          "player_position": ""
        },
        "player_id": 6028,
        "captain": false,
        "leagueyearteamplayer_id": 7160,
        "leagueyearteam_id": 239,
        "clubplayer_id": null,
        "player_jersey": null
      },
      {
        "Player": {
          "player_id": 6030,
          "PlayerName": "李科燈",
          "player_position": ""
        },
        "player_id": 6030,
        "captain": false,
        "leagueyearteamplayer_id": 7157,
        "leagueyearteam_id": 239,
        "clubplayer_id": null,
        "player_jersey": null
      },
      {
        "Player": {
          "player_id": 6021,
          "PlayerName": "梁志恒",
          "player_position": ""
        },
        "player_id": 6021,
        "captain": false,
        "leagueyearteamplayer_id": 7161,
        "leagueyearteam_id": 239,
        "clubplayer_id": null,
        "player_jersey": null
      },
      {
        "Player": {
          "player_id": 6023,
          "PlayerName": "呂煥文",
          "player_position": ""
        },
        "player_id": 6023,
        "captain": false,
        "leagueyearteamplayer_id": 7155,
        "leagueyearteam_id": 239,
        "clubplayer_id": null,
        "player_jersey": null
      },
      {
        "Player": {
          "player_id": 6022,
          "PlayerName": "麥國祥",
          "player_position": ""
        },
        "player_id": 6022,
        "captain": true,
        "leagueyearteamplayer_id": 7151,
        "leagueyearteam_id": 239,
        "clubplayer_id": null,
        "player_jersey": null
      },
      {
        "Player": {
          "player_id": 6032,
          "PlayerName": "麥子豐",
          "player_position": ""
        },
        "player_id": 6032,
        "captain": false,
        "leagueyearteamplayer_id": 7152,
        "leagueyearteam_id": 239,
        "clubplayer_id": null,
        "player_jersey": null
      },
      {
        "Player": {
          "player_id": 5168,
          "PlayerName": "吳家銘",
          "player_position": ""
        },
        "player_id": 5168,
        "captain": false,
        "leagueyearteamplayer_id": 7154,
        "leagueyearteam_id": 239,
        "clubplayer_id": null,
        "player_jersey": null
      },
      {
        "Player": {
          "player_id": 6020,
          "PlayerName": "伍家榮",
          "player_position": ""
        },
        "player_id": 6020,
        "captain": false,
        "leagueyearteamplayer_id": 7164,
        "leagueyearteam_id": 239,
        "clubplayer_id": null,
        "player_jersey": null
      },
      {
        "Player": {
          "player_id": 3889,
          "PlayerName": "杜汝燊",
          "player_position": ""
        },
        "player_id": 3889,
        "captain": false,
        "leagueyearteamplayer_id": 7159,
        "leagueyearteam_id": 239,
        "clubplayer_id": null,
        "player_jersey": null
      },
      {
        "Player": {
          "player_id": 6025,
          "PlayerName": "殷偉民",
          "player_position": ""
        },
        "player_id": 6025,
        "captain": false,
        "leagueyearteamplayer_id": 7163,
        "leagueyearteam_id": 239,
        "clubplayer_id": null,
        "player_jersey": null
      }
    ],
    "GuestSubPlayers": [
      {
        "Player": {
          "player_id": 6031,
          "PlayerName": "黃愷利",
          "player_position": ""
        },
        "player_id": 6031,
        "captain": false,
        "leagueyearteamplayer_id": 7153,
        "leagueyearteam_id": 239,
        "clubplayer_id": null,
        "player_jersey": null
      },
      {
        "Player": {
          "player_id": 6026,
          "PlayerName": "高天賜",
          "player_position": ""
        },
        "player_id": 6026,
        "captain": false,
        "leagueyearteamplayer_id": 7150,
        "leagueyearteam_id": 239,
        "clubplayer_id": null,
        "player_jersey": null
      },
      {
        "Player": {
          "player_id": 6029,
          "PlayerName": "馬浩斌",
          "player_position": ""
        },
        "player_id": 6029,
        "captain": false,
        "leagueyearteamplayer_id": 7149,
        "leagueyearteam_id": 239,
        "clubplayer_id": null,
        "player_jersey": null
      },
      {
        "Player": {
          "player_id": 3768,
          "PlayerName": "馬家億",
          "player_position": ""
        },
        "player_id": 3768,
        "captain": false,
        "leagueyearteamplayer_id": 7148,
        "leagueyearteam_id": 239,
        "clubplayer_id": null,
        "player_jersey": null
      },
      {
        "Player": {
          "player_id": 6033,
          "PlayerName": "彭正傑",
          "player_position": ""
        },
        "player_id": 6033,
        "captain": false,
        "leagueyearteamplayer_id": 7156,
        "leagueyearteam_id": 239,
        "clubplayer_id": null,
        "player_jersey": null
      }
    ],
    "MatchEvents": [
      {
        "teamplayer_home_id": 7130,
        "teamplayer_home_sub_id": 0,
        "teamplayer_guest_id": 0,
        "teamplayer_guest_sub_id": 0,
        "teamplayer_home": {
          "player_id": 4816,
          "club_id": 0,
          "PlayerName": "駱旭文",
          "player_position": ""
        },
        "teamplayer_home_sub": null,
        "teamplayer_guest": null,
        "teamplayer_guest_sub": null,
        "EventType": "G",
        "side": "Home",
        "min": 8,
        "minExtra": 0,
        "EXCPlayer": null
      },
      {
        "teamplayer_home_id": 0,
        "teamplayer_home_sub_id": 0,
        "teamplayer_guest_id": 7155,
        "teamplayer_guest_sub_id": 0,
        "teamplayer_home": null,
        "teamplayer_home_sub": null,
        "teamplayer_guest": {
          "player_id": 6023,
          "club_id": 0,
          "PlayerName": "呂煥文",
          "player_position": ""
        },
        "teamplayer_guest_sub": null,
        "EventType": "G",
        "side": "Guest",
        "min": 37,
        "minExtra": 0,
        "EXCPlayer": null
      },
      {
        "teamplayer_home_id": 0,
        "teamplayer_home_sub_id": 0,
        "teamplayer_guest_id": 7159,
        "teamplayer_guest_sub_id": 0,
        "teamplayer_home": null,
        "teamplayer_home_sub": null,
        "teamplayer_guest": {
          "player_id": 3889,
          "club_id": 0,
          "PlayerName": "杜汝燊",
          "player_position": ""
        },
        "teamplayer_guest_sub": null,
        "EventType": "YC",
        "side": "Guest",
        "min": 16,
        "minExtra": 0,
        "EXCPlayer": null
      },
      {
        "teamplayer_home_id": 7128,
        "teamplayer_home_sub_id": 0,
        "teamplayer_guest_id": 0,
        "teamplayer_guest_sub_id": 0,
        "teamplayer_home": {
          "player_id": 4032,
          "club_id": 0,
          "PlayerName": "阮國威",
          "player_position": ""
        },
        "teamplayer_home_sub": null,
        "teamplayer_guest": null,
        "teamplayer_guest_sub": null,
        "EventType": "YC",
        "side": "Home",
        "min": 37,
        "minExtra": 0,
        "EXCPlayer": null
      },
      {
        "teamplayer_home_id": 7128,
        "teamplayer_home_sub_id": 0,
        "teamplayer_guest_id": 0,
        "teamplayer_guest_sub_id": 0,
        "teamplayer_home": {
          "player_id": 4032,
          "club_id": 0,
          "PlayerName": "阮國威",
          "player_position": ""
        },
        "teamplayer_home_sub": null,
        "teamplayer_guest": null,
        "teamplayer_guest_sub": null,
        "EventType": "YC",
        "side": "Home",
        "min": 43,
        "minExtra": 0,
        "EXCPlayer": null
      },
      {
        "teamplayer_home_id": 7143,
        "teamplayer_home_sub_id": 0,
        "teamplayer_guest_id": 0,
        "teamplayer_guest_sub_id": 0,
        "teamplayer_home": {
          "player_id": 4020,
          "club_id": 0,
          "PlayerName": "何偉立",
          "player_position": ""
        },
        "teamplayer_home_sub": null,
        "teamplayer_guest": null,
        "teamplayer_guest_sub": null,
        "EventType": "YC",
        "side": "Home",
        "min": 51,
        "minExtra": 0,
        "EXCPlayer": null
      },
      {
        "teamplayer_home_id": 7135,
        "teamplayer_home_sub_id": 0,
        "teamplayer_guest_id": 0,
        "teamplayer_guest_sub_id": 0,
        "teamplayer_home": {
          "player_id": 4028,
          "club_id": 0,
          "PlayerName": "吳志豪",
          "player_position": ""
        },
        "teamplayer_home_sub": null,
        "teamplayer_guest": null,
        "teamplayer_guest_sub": null,
        "EventType": "YC",
        "side": "Home",
        "min": 76,
        "minExtra": 0,
        "EXCPlayer": null
      },
      {
        "teamplayer_home_id": 0,
        "teamplayer_home_sub_id": 0,
        "teamplayer_guest_id": 7147,
        "teamplayer_guest_sub_id": 0,
        "teamplayer_home": null,
        "teamplayer_home_sub": null,
        "teamplayer_guest": {
          "player_id": 6027,
          "club_id": 0,
          "PlayerName": "郭志文",
          "player_position": ""
        },
        "teamplayer_guest_sub": null,
        "EventType": "YC",
        "side": "Guest",
        "min": 90,
        "minExtra": 0,
        "EXCPlayer": null
      },
      {
        "teamplayer_home_id": 7128,
        "teamplayer_home_sub_id": 0,
        "teamplayer_guest_id": 0,
        "teamplayer_guest_sub_id": 0,
        "teamplayer_home": {
          "player_id": 4032,
          "club_id": 0,
          "PlayerName": "阮國威",
          "player_position": ""
        },
        "teamplayer_home_sub": null,
        "teamplayer_guest": null,
        "teamplayer_guest_sub": null,
        "EventType": "RC",
        "side": "Home",
        "min": 43,
        "minExtra": 0,
        "EXCPlayer": null
      },
      {
        "teamplayer_home_id": 0,
        "teamplayer_home_sub_id": 0,
        "teamplayer_guest_id": 7148,
        "teamplayer_guest_sub_id": 7160,
        "teamplayer_home": null,
        "teamplayer_home_sub": null,
        "teamplayer_guest": {
          "player_id": 3768,
          "club_id": 0,
          "PlayerName": "馬家億",
          "player_position": ""
        },
        "teamplayer_guest_sub": {
          "player_id": 6028,
          "club_id": 0,
          "PlayerName": "林浩賢",
          "player_position": ""
        },
        "EventType": "EXC",
        "side": "Guest",
        "min": 29,
        "minExtra": 0,
        "EXCPlayer": {
          "side": "Guest",
          "from": {
            "Player": {
              "PlayerName": "馬家億",
              "player_position": ""
            },
            "player_id": 3768,
            "leagueyearteamplayer_id": 7148,
            "leagueyearteam_id": 239,
            "clubplayer_id": null,
            "player_jersey": null
          },
          "to": {
            "Player": {
              "PlayerName": "林浩賢",
              "player_position": ""
            },
            "player_id": 6028,
            "leagueyearteamplayer_id": 7160,
            "leagueyearteam_id": 239,
            "clubplayer_id": null,
            "player_jersey": null
          }
        }
      },
      {
        "teamplayer_home_id": 0,
        "teamplayer_home_sub_id": 0,
        "teamplayer_guest_id": 7153,
        "teamplayer_guest_sub_id": 7148,
        "teamplayer_home": null,
        "teamplayer_home_sub": null,
        "teamplayer_guest": {
          "player_id": 6031,
          "club_id": 0,
          "PlayerName": "黃愷利",
          "player_position": ""
        },
        "teamplayer_guest_sub": {
          "player_id": 3768,
          "club_id": 0,
          "PlayerName": "馬家億",
          "player_position": ""
        },
        "EventType": "EXC",
        "side": "Guest",
        "min": 43,
        "minExtra": 0,
        "EXCPlayer": {
          "side": "Guest",
          "from": {
            "Player": {
              "PlayerName": "黃愷利",
              "player_position": ""
            },
            "player_id": 6031,
            "leagueyearteamplayer_id": 7153,
            "leagueyearteam_id": 239,
            "clubplayer_id": null,
            "player_jersey": null
          },
          "to": {
            "Player": {
              "PlayerName": "馬家億",
              "player_position": ""
            },
            "player_id": 3768,
            "leagueyearteamplayer_id": 7148,
            "leagueyearteam_id": 239,
            "clubplayer_id": null,
            "player_jersey": null
          }
        }
      },
      {
        "teamplayer_home_id": 7131,
        "teamplayer_home_sub_id": 7130,
        "teamplayer_guest_id": 0,
        "teamplayer_guest_sub_id": 0,
        "teamplayer_home": {
          "player_id": 4817,
          "club_id": 0,
          "PlayerName": "賴志偉",
          "player_position": ""
        },
        "teamplayer_home_sub": {
          "player_id": 4816,
          "club_id": 0,
          "PlayerName": "駱旭文",
          "player_position": ""
        },
        "teamplayer_guest": null,
        "teamplayer_guest_sub": null,
        "EventType": "EXC",
        "side": "Home",
        "min": 44,
        "minExtra": 0,
        "EXCPlayer": {
          "side": "Home",
          "from": {
            "Player": {
              "PlayerName": "賴志偉",
              "player_position": ""
            },
            "player_id": 4817,
            "leagueyearteamplayer_id": 7131,
            "leagueyearteam_id": 238,
            "clubplayer_id": null,
            "player_jersey": null
          },
          "to": {
            "Player": {
              "PlayerName": "駱旭文",
              "player_position": ""
            },
            "player_id": 4816,
            "leagueyearteamplayer_id": 7130,
            "leagueyearteam_id": 238,
            "clubplayer_id": null,
            "player_jersey": null
          }
        }
      },
      {
        "teamplayer_home_id": 0,
        "teamplayer_home_sub_id": 0,
        "teamplayer_guest_id": 7149,
        "teamplayer_guest_sub_id": 7152,
        "teamplayer_home": null,
        "teamplayer_home_sub": null,
        "teamplayer_guest": {
          "player_id": 6029,
          "club_id": 0,
          "PlayerName": "馬浩斌",
          "player_position": ""
        },
        "teamplayer_guest_sub": {
          "player_id": 6032,
          "club_id": 0,
          "PlayerName": "麥子豐",
          "player_position": ""
        },
        "EventType": "EXC",
        "side": "Guest",
        "min": 46,
        "minExtra": 0,
        "EXCPlayer": {
          "side": "Guest",
          "from": {
            "Player": {
              "PlayerName": "馬浩斌",
              "player_position": ""
            },
            "player_id": 6029,
            "leagueyearteamplayer_id": 7149,
            "leagueyearteam_id": 239,
            "clubplayer_id": null,
            "player_jersey": null
          },
          "to": {
            "Player": {
              "PlayerName": "麥子豐",
              "player_position": ""
            },
            "player_id": 6032,
            "leagueyearteamplayer_id": 7152,
            "leagueyearteam_id": 239,
            "clubplayer_id": null,
            "player_jersey": null
          }
        }
      },
      {
        "teamplayer_home_id": 7140,
        "teamplayer_home_sub_id": 7143,
        "teamplayer_guest_id": 0,
        "teamplayer_guest_sub_id": 0,
        "teamplayer_home": {
          "player_id": 4026,
          "club_id": 0,
          "PlayerName": "李凱俊",
          "player_position": ""
        },
        "teamplayer_home_sub": {
          "player_id": 4020,
          "club_id": 0,
          "PlayerName": "何偉立",
          "player_position": ""
        },
        "teamplayer_guest": null,
        "teamplayer_guest_sub": null,
        "EventType": "EXC",
        "side": "Home",
        "min": 58,
        "minExtra": 0,
        "EXCPlayer": {
          "side": "Home",
          "from": {
            "Player": {
              "PlayerName": "李凱俊",
              "player_position": ""
            },
            "player_id": 4026,
            "leagueyearteamplayer_id": 7140,
            "leagueyearteam_id": 238,
            "clubplayer_id": null,
            "player_jersey": null
          },
          "to": {
            "Player": {
              "PlayerName": "何偉立",
              "player_position": ""
            },
            "player_id": 4020,
            "leagueyearteamplayer_id": 7143,
            "leagueyearteam_id": 238,
            "clubplayer_id": null,
            "player_jersey": "0"
          }
        }
      },
      {
        "teamplayer_home_id": 7142,
        "teamplayer_home_sub_id": 7126,
        "teamplayer_guest_id": 0,
        "teamplayer_guest_sub_id": 0,
        "teamplayer_home": {
          "player_id": 4815,
          "club_id": 0,
          "PlayerName": "梁樂倫",
          "player_position": ""
        },
        "teamplayer_home_sub": {
          "player_id": 4021,
          "club_id": 0,
          "PlayerName": "葉俊文",
          "player_position": ""
        },
        "teamplayer_guest": null,
        "teamplayer_guest_sub": null,
        "EventType": "EXC",
        "side": "Home",
        "min": 80,
        "minExtra": 0,
        "EXCPlayer": {
          "side": "Home",
          "from": {
            "Player": {
              "PlayerName": "梁樂倫",
              "player_position": ""
            },
            "player_id": 4815,
            "leagueyearteamplayer_id": 7142,
            "leagueyearteam_id": 238,
            "clubplayer_id": null,
            "player_jersey": "0"
          },
          "to": {
            "Player": {
              "PlayerName": "葉俊文",
              "player_position": ""
            },
            "player_id": 4021,
            "leagueyearteamplayer_id": 7126,
            "leagueyearteam_id": 238,
            "clubplayer_id": null,
            "player_jersey": null
          }
        }
      }
    ],
    "report": {
      "news_id": null,
      "news_date": null,
      "news_title": null,
      "news_abstract": null,
      "news_content": null,
      "news_image_1": null,
      "news_image_2": null,
      "news_image_3": null,
      "news_image_4": null,
      "news_image_5": null,
      "news_image_6": null,
      "news_league": null,
      "news_hkteam_type": null
    }
  },
  "HomePlayersTable": [
    {
      "Player": {
        "player_id": 6011,
        "PlayerName": "王偉成",
        "player_position": ""
      },
      "player_id": 6011,
      "captain": false,
      "leagueyearteamplayer_id": 7122,
      "leagueyearteam_id": 238,
      "clubplayer_id": null,
      "player_jersey": null
    },
    {
      "Player": {
        "player_id": 6019,
        "PlayerName": "周志豪",
        "player_position": ""
      },
      "player_id": 6019,
      "captain": false,
      "leagueyearteamplayer_id": 7138,
      "leagueyearteam_id": 238,
      "clubplayer_id": null,
      "player_jersey": null
    },
    {
      "Player": {
        "player_id": 4023,
        "PlayerName": "周劍鋒",
        "player_position": ""
      },
      "player_id": 4023,
      "captain": false,
      "leagueyearteamplayer_id": 7136,
      "leagueyearteam_id": 238,
      "clubplayer_id": null,
      "player_jersey": null
    },
    {
      "Player": {
        "player_id": 4020,
        "PlayerName": "何偉立",
        "player_position": ""
      },
      "player_id": 4020,
      "captain": true,
      "leagueyearteamplayer_id": 7143,
      "leagueyearteam_id": 238,
      "clubplayer_id": null,
      "player_jersey": "0"
    },
    {
      "Player": {
        "player_id": 4021,
        "PlayerName": "葉俊文",
        "player_position": ""
      },
      "player_id": 4021,
      "captain": false,
      "leagueyearteamplayer_id": 7126,
      "leagueyearteam_id": 238,
      "clubplayer_id": null,
      "player_jersey": null
    },
    {
      "Player": {
        "player_id": 4018,
        "PlayerName": "鄺禮健",
        "player_position": ""
      },
      "player_id": 4018,
      "captain": false,
      "leagueyearteamplayer_id": 7125,
      "leagueyearteam_id": 238,
      "clubplayer_id": null,
      "player_jersey": null
    },
    {
      "Player": {
        "player_id": 4816,
        "PlayerName": "駱旭文",
        "player_position": ""
      },
      "player_id": 4816,
      "captain": false,
      "leagueyearteamplayer_id": 7130,
      "leagueyearteam_id": 238,
      "clubplayer_id": null,
      "player_jersey": null
    },
    {
      "Player": {
        "player_id": 4028,
        "PlayerName": "吳志豪",
        "player_position": ""
      },
      "player_id": 4028,
      "captain": false,
      "leagueyearteamplayer_id": 7135,
      "leagueyearteam_id": 238,
      "clubplayer_id": null,
      "player_jersey": null
    },
    {
      "Player": {
        "player_id": 6017,
        "PlayerName": "潘兆恒",
        "player_position": ""
      },
      "player_id": 6017,
      "captain": false,
      "leagueyearteamplayer_id": 7145,
      "leagueyearteam_id": 238,
      "clubplayer_id": null,
      "player_jersey": null
    },
    {
      "Player": {
        "player_id": 6014,
        "PlayerName": "胡慶龍",
        "player_position": ""
      },
      "player_id": 6014,
      "captain": false,
      "leagueyearteamplayer_id": 7124,
      "leagueyearteam_id": 238,
      "clubplayer_id": null,
      "player_jersey": null
    },
    {
      "Player": {
        "player_id": 4032,
        "PlayerName": "阮國威",
        "player_position": ""
      },
      "player_id": 4032,
      "captain": false,
      "leagueyearteamplayer_id": 7128,
      "leagueyearteam_id": 238,
      "clubplayer_id": null,
      "player_jersey": null
    }
  ],
  "GuestPlayersTable": [
    {
      "Player": {
        "player_id": 6027,
        "PlayerName": "郭志文",
        "player_position": ""
      },
      "player_id": 6027,
      "captain": false,
      "leagueyearteamplayer_id": 7147,
      "leagueyearteam_id": 239,
      "clubplayer_id": null,
      "player_jersey": null
    },
    {
      "Player": {
        "player_id": 6028,
        "PlayerName": "林浩賢",
        "player_position": ""
      },
      "player_id": 6028,
      "captain": false,
      "leagueyearteamplayer_id": 7160,
      "leagueyearteam_id": 239,
      "clubplayer_id": null,
      "player_jersey": null
    },
    {
      "Player": {
        "player_id": 6030,
        "PlayerName": "李科燈",
        "player_position": ""
      },
      "player_id": 6030,
      "captain": false,
      "leagueyearteamplayer_id": 7157,
      "leagueyearteam_id": 239,
      "clubplayer_id": null,
      "player_jersey": null
    },
    {
      "Player": {
        "player_id": 6021,
        "PlayerName": "梁志恒",
        "player_position": ""
      },
      "player_id": 6021,
      "captain": false,
      "leagueyearteamplayer_id": 7161,
      "leagueyearteam_id": 239,
      "clubplayer_id": null,
      "player_jersey": null
    },
    {
      "Player": {
        "player_id": 6023,
        "PlayerName": "呂煥文",
        "player_position": ""
      },
      "player_id": 6023,
      "captain": false,
      "leagueyearteamplayer_id": 7155,
      "leagueyearteam_id": 239,
      "clubplayer_id": null,
      "player_jersey": null
    },
    {
      "Player": {
        "player_id": 6022,
        "PlayerName": "麥國祥",
        "player_position": ""
      },
      "player_id": 6022,
      "captain": true,
      "leagueyearteamplayer_id": 7151,
      "leagueyearteam_id": 239,
      "clubplayer_id": null,
      "player_jersey": null
    },
    {
      "Player": {
        "player_id": 6032,
        "PlayerName": "麥子豐",
        "player_position": ""
      },
      "player_id": 6032,
      "captain": false,
      "leagueyearteamplayer_id": 7152,
      "leagueyearteam_id": 239,
      "clubplayer_id": null,
      "player_jersey": null
    },
    {
      "Player": {
        "player_id": 5168,
        "PlayerName": "吳家銘",
        "player_position": ""
      },
      "player_id": 5168,
      "captain": false,
      "leagueyearteamplayer_id": 7154,
      "leagueyearteam_id": 239,
      "clubplayer_id": null,
      "player_jersey": null
    },
    {
      "Player": {
        "player_id": 6020,
        "PlayerName": "伍家榮",
        "player_position": ""
      },
      "player_id": 6020,
      "captain": false,
      "leagueyearteamplayer_id": 7164,
      "leagueyearteam_id": 239,
      "clubplayer_id": null,
      "player_jersey": null
    },
    {
      "Player": {
        "player_id": 3889,
        "PlayerName": "杜汝燊",
        "player_position": ""
      },
      "player_id": 3889,
      "captain": false,
      "leagueyearteamplayer_id": 7159,
      "leagueyearteam_id": 239,
      "clubplayer_id": null,
      "player_jersey": null
    },
    {
      "Player": {
        "player_id": 6025,
        "PlayerName": "殷偉民",
        "player_position": ""
      },
      "player_id": 6025,
      "captain": false,
      "leagueyearteamplayer_id": 7163,
      "leagueyearteam_id": 239,
      "clubplayer_id": null,
      "player_jersey": null
    }
  ],
  "HomeSubPlayersTable": [
    {
      "Player": {
        "player_id": 4029,
        "PlayerName": "何偉健",
        "player_position": ""
      },
      "player_id": 4029,
      "captain": false,
      "leagueyearteamplayer_id": 7144,
      "leagueyearteam_id": 238,
      "clubplayer_id": null,
      "player_jersey": null
    },
    {
      "Player": {
        "player_id": 4817,
        "PlayerName": "賴志偉",
        "player_position": ""
      },
      "player_id": 4817,
      "captain": false,
      "leagueyearteamplayer_id": 7131,
      "leagueyearteam_id": 238,
      "clubplayer_id": null,
      "player_jersey": null
    },
    {
      "Player": {
        "player_id": 4938,
        "PlayerName": "黎振康",
        "player_position": ""
      },
      "player_id": 4938,
      "captain": false,
      "leagueyearteamplayer_id": 7133,
      "leagueyearteam_id": 238,
      "clubplayer_id": null,
      "player_jersey": null
    },
    {
      "Player": {
        "player_id": 6013,
        "PlayerName": "林肇璞",
        "player_position": ""
      },
      "player_id": 6013,
      "captain": false,
      "leagueyearteamplayer_id": 7141,
      "leagueyearteam_id": 238,
      "clubplayer_id": null,
      "player_jersey": null
    },
    {
      "Player": {
        "player_id": 4815,
        "PlayerName": "梁樂倫",
        "player_position": ""
      },
      "player_id": 4815,
      "captain": false,
      "leagueyearteamplayer_id": 7142,
      "leagueyearteam_id": 238,
      "clubplayer_id": null,
      "player_jersey": "0"
    },
    {
      "Player": {
        "player_id": 4026,
        "PlayerName": "李凱俊",
        "player_position": ""
      },
      "player_id": 4026,
      "captain": false,
      "leagueyearteamplayer_id": 7140,
      "leagueyearteam_id": 238,
      "clubplayer_id": null,
      "player_jersey": null
    },
    {
      "Player": {
        "player_id": 4034,
        "PlayerName": "黃牖良",
        "player_position": ""
      },
      "player_id": 4034,
      "captain": false,
      "leagueyearteamplayer_id": 7132,
      "leagueyearteam_id": 238,
      "clubplayer_id": null,
      "player_jersey": null
    }
  ],
  "GuestSubPlayersTable": [
    {
      "Player": {
        "player_id": 6031,
        "PlayerName": "黃愷利",
        "player_position": ""
      },
      "player_id": 6031,
      "captain": false,
      "leagueyearteamplayer_id": 7153,
      "leagueyearteam_id": 239,
      "clubplayer_id": null,
      "player_jersey": null
    },
    {
      "Player": {
        "player_id": 6026,
        "PlayerName": "高天賜",
        "player_position": ""
      },
      "player_id": 6026,
      "captain": false,
      "leagueyearteamplayer_id": 7150,
      "leagueyearteam_id": 239,
      "clubplayer_id": null,
      "player_jersey": null
    },
    {
      "Player": {
        "player_id": 6029,
        "PlayerName": "馬浩斌",
        "player_position": ""
      },
      "player_id": 6029,
      "captain": false,
      "leagueyearteamplayer_id": 7149,
      "leagueyearteam_id": 239,
      "clubplayer_id": null,
      "player_jersey": null
    },
    {
      "Player": {
        "player_id": 3768,
        "PlayerName": "馬家億",
        "player_position": ""
      },
      "player_id": 3768,
      "captain": false,
      "leagueyearteamplayer_id": 7148,
      "leagueyearteam_id": 239,
      "clubplayer_id": null,
      "player_jersey": null
    },
    {
      "Player": {
        "player_id": 6033,
        "PlayerName": "彭正傑",
        "player_position": ""
      },
      "player_id": 6033,
      "captain": false,
      "leagueyearteamplayer_id": 7156,
      "leagueyearteam_id": 239,
      "clubplayer_id": null,
      "player_jersey": null
    }
  ],
  "HomeStatisticTable": {
    "shoot": null,
    "shoot_on_target": null,
    "corner": null,
    "offside": null,
    "fouls": null,
    "saves": null,
    "yc": 4,
    "rc": 1
  },
  "GuestStatisticTable": {
    "shoot": null,
    "shoot_on_target": null,
    "corner": null,
    "offside": null,
    "fouls": null,
    "saves": null,
    "yc": 2,
    "rc": 0
  },
  "HomeGoalPlayerTable": [
    {
      "teamplayer_home_id": 7130,
      "teamplayer_home_sub_id": 0,
      "teamplayer_guest_id": 0,
      "teamplayer_guest_sub_id": 0,
      "teamplayer_home": {
        "player_id": 4816,
        "club_id": 0,
        "PlayerName": "駱旭文",
        "player_position": ""
      },
      "teamplayer_home_sub": null,
      "teamplayer_guest": null,
      "teamplayer_guest_sub": null,
      "EventType": "G",
      "side": "Home",
      "min": 8,
      "minExtra": 0,
      "EXCPlayer": null
    }
  ],
  "GuestGoalPlayerTable": [
    {
      "teamplayer_home_id": 0,
      "teamplayer_home_sub_id": 0,
      "teamplayer_guest_id": 7155,
      "teamplayer_guest_sub_id": 0,
      "teamplayer_home": null,
      "teamplayer_home_sub": null,
      "teamplayer_guest": {
        "player_id": 6023,
        "club_id": 0,
        "PlayerName": "呂煥文",
        "player_position": ""
      },
      "teamplayer_guest_sub": null,
      "EventType": "G",
      "side": "Guest",
      "min": 37,
      "minExtra": 0,
      "EXCPlayer": null
    }
  ],
  "Home12YPlayerTable": [],
  "Guest12YPlayerTable": [],
  "HomeYCTable": [
    {
      "teamplayer_home_id": 7128,
      "teamplayer_home_sub_id": 0,
      "teamplayer_guest_id": 0,
      "teamplayer_guest_sub_id": 0,
      "teamplayer_home": {
        "player_id": 4032,
        "club_id": 0,
        "PlayerName": "阮國威",
        "player_position": ""
      },
      "teamplayer_home_sub": null,
      "teamplayer_guest": null,
      "teamplayer_guest_sub": null,
      "EventType": "YC",
      "side": "Home",
      "min": 37,
      "minExtra": 0,
      "EXCPlayer": null
    },
    {
      "teamplayer_home_id": 7128,
      "teamplayer_home_sub_id": 0,
      "teamplayer_guest_id": 0,
      "teamplayer_guest_sub_id": 0,
      "teamplayer_home": {
        "player_id": 4032,
        "club_id": 0,
        "PlayerName": "阮國威",
        "player_position": ""
      },
      "teamplayer_home_sub": null,
      "teamplayer_guest": null,
      "teamplayer_guest_sub": null,
      "EventType": "YC",
      "side": "Home",
      "min": 43,
      "minExtra": 0,
      "EXCPlayer": null
    },
    {
      "teamplayer_home_id": 7143,
      "teamplayer_home_sub_id": 0,
      "teamplayer_guest_id": 0,
      "teamplayer_guest_sub_id": 0,
      "teamplayer_home": {
        "player_id": 4020,
        "club_id": 0,
        "PlayerName": "何偉立",
        "player_position": ""
      },
      "teamplayer_home_sub": null,
      "teamplayer_guest": null,
      "teamplayer_guest_sub": null,
      "EventType": "YC",
      "side": "Home",
      "min": 51,
      "minExtra": 0,
      "EXCPlayer": null
    },
    {
      "teamplayer_home_id": 7135,
      "teamplayer_home_sub_id": 0,
      "teamplayer_guest_id": 0,
      "teamplayer_guest_sub_id": 0,
      "teamplayer_home": {
        "player_id": 4028,
        "club_id": 0,
        "PlayerName": "吳志豪",
        "player_position": ""
      },
      "teamplayer_home_sub": null,
      "teamplayer_guest": null,
      "teamplayer_guest_sub": null,
      "EventType": "YC",
      "side": "Home",
      "min": 76,
      "minExtra": 0,
      "EXCPlayer": null
    }
  ],
  "GuestYCTable": [
    {
      "teamplayer_home_id": 0,
      "teamplayer_home_sub_id": 0,
      "teamplayer_guest_id": 7159,
      "teamplayer_guest_sub_id": 0,
      "teamplayer_home": null,
      "teamplayer_home_sub": null,
      "teamplayer_guest": {
        "player_id": 3889,
        "club_id": 0,
        "PlayerName": "杜汝燊",
        "player_position": ""
      },
      "teamplayer_guest_sub": null,
      "EventType": "YC",
      "side": "Guest",
      "min": 16,
      "minExtra": 0,
      "EXCPlayer": null
    },
    {
      "teamplayer_home_id": 0,
      "teamplayer_home_sub_id": 0,
      "teamplayer_guest_id": 7147,
      "teamplayer_guest_sub_id": 0,
      "teamplayer_home": null,
      "teamplayer_home_sub": null,
      "teamplayer_guest": {
        "player_id": 6027,
        "club_id": 0,
        "PlayerName": "郭志文",
        "player_position": ""
      },
      "teamplayer_guest_sub": null,
      "EventType": "YC",
      "side": "Guest",
      "min": 90,
      "minExtra": 0,
      "EXCPlayer": null
    }
  ],
  "HomeRCTable": [
    {
      "teamplayer_home_id": 7128,
      "teamplayer_home_sub_id": 0,
      "teamplayer_guest_id": 0,
      "teamplayer_guest_sub_id": 0,
      "teamplayer_home": {
        "player_id": 4032,
        "club_id": 0,
        "PlayerName": "阮國威",
        "player_position": ""
      },
      "teamplayer_home_sub": null,
      "teamplayer_guest": null,
      "teamplayer_guest_sub": null,
      "EventType": "RC",
      "side": "Home",
      "min": 43,
      "minExtra": 0,
      "EXCPlayer": null
    }
  ],
  "GuestRCTable": [],
  "HomeEXCTable": [
    {
      "teamplayer_home_id": 7131,
      "teamplayer_home_sub_id": 7130,
      "teamplayer_guest_id": 0,
      "teamplayer_guest_sub_id": 0,
      "teamplayer_home": {
        "player_id": 4817,
        "club_id": 0,
        "PlayerName": "賴志偉",
        "player_position": ""
      },
      "teamplayer_home_sub": {
        "player_id": 4816,
        "club_id": 0,
        "PlayerName": "駱旭文",
        "player_position": ""
      },
      "teamplayer_guest": null,
      "teamplayer_guest_sub": null,
      "EventType": "EXC",
      "side": "Home",
      "min": 44,
      "minExtra": 0,
      "EXCPlayer": {
        "side": "Home",
        "from": {
          "Player": {
            "PlayerName": "賴志偉",
            "player_position": ""
          },
          "player_id": 4817,
          "leagueyearteamplayer_id": 7131,
          "leagueyearteam_id": 238,
          "clubplayer_id": null,
          "player_jersey": null
        },
        "to": {
          "Player": {
            "PlayerName": "駱旭文",
            "player_position": ""
          },
          "player_id": 4816,
          "leagueyearteamplayer_id": 7130,
          "leagueyearteam_id": 238,
          "clubplayer_id": null,
          "player_jersey": null
        }
      }
    },
    {
      "teamplayer_home_id": 7140,
      "teamplayer_home_sub_id": 7143,
      "teamplayer_guest_id": 0,
      "teamplayer_guest_sub_id": 0,
      "teamplayer_home": {
        "player_id": 4026,
        "club_id": 0,
        "PlayerName": "李凱俊",
        "player_position": ""
      },
      "teamplayer_home_sub": {
        "player_id": 4020,
        "club_id": 0,
        "PlayerName": "何偉立",
        "player_position": ""
      },
      "teamplayer_guest": null,
      "teamplayer_guest_sub": null,
      "EventType": "EXC",
      "side": "Home",
      "min": 58,
      "minExtra": 0,
      "EXCPlayer": {
        "side": "Home",
        "from": {
          "Player": {
            "PlayerName": "李凱俊",
            "player_position": ""
          },
          "player_id": 4026,
          "leagueyearteamplayer_id": 7140,
          "leagueyearteam_id": 238,
          "clubplayer_id": null,
          "player_jersey": null
        },
        "to": {
          "Player": {
            "PlayerName": "何偉立",
            "player_position": ""
          },
          "player_id": 4020,
          "leagueyearteamplayer_id": 7143,
          "leagueyearteam_id": 238,
          "clubplayer_id": null,
          "player_jersey": "0"
        }
      }
    },
    {
      "teamplayer_home_id": 7142,
      "teamplayer_home_sub_id": 7126,
      "teamplayer_guest_id": 0,
      "teamplayer_guest_sub_id": 0,
      "teamplayer_home": {
        "player_id": 4815,
        "club_id": 0,
        "PlayerName": "梁樂倫",
        "player_position": ""
      },
      "teamplayer_home_sub": {
        "player_id": 4021,
        "club_id": 0,
        "PlayerName": "葉俊文",
        "player_position": ""
      },
      "teamplayer_guest": null,
      "teamplayer_guest_sub": null,
      "EventType": "EXC",
      "side": "Home",
      "min": 80,
      "minExtra": 0,
      "EXCPlayer": {
        "side": "Home",
        "from": {
          "Player": {
            "PlayerName": "梁樂倫",
            "player_position": ""
          },
          "player_id": 4815,
          "leagueyearteamplayer_id": 7142,
          "leagueyearteam_id": 238,
          "clubplayer_id": null,
          "player_jersey": "0"
        },
        "to": {
          "Player": {
            "PlayerName": "葉俊文",
            "player_position": ""
          },
          "player_id": 4021,
          "leagueyearteamplayer_id": 7126,
          "leagueyearteam_id": 238,
          "clubplayer_id": null,
          "player_jersey": null
        }
      }
    }
  ],
  "GuestEXCTable": [
    {
      "teamplayer_home_id": 0,
      "teamplayer_home_sub_id": 0,
      "teamplayer_guest_id": 7148,
      "teamplayer_guest_sub_id": 7160,
      "teamplayer_home": null,
      "teamplayer_home_sub": null,
      "teamplayer_guest": {
        "player_id": 3768,
        "club_id": 0,
        "PlayerName": "馬家億",
        "player_position": ""
      },
      "teamplayer_guest_sub": {
        "player_id": 6028,
        "club_id": 0,
        "PlayerName": "林浩賢",
        "player_position": ""
      },
      "EventType": "EXC",
      "side": "Guest",
      "min": 29,
      "minExtra": 0,
      "EXCPlayer": {
        "side": "Guest",
        "from": {
          "Player": {
            "PlayerName": "馬家億",
            "player_position": ""
          },
          "player_id": 3768,
          "leagueyearteamplayer_id": 7148,
          "leagueyearteam_id": 239,
          "clubplayer_id": null,
          "player_jersey": null
        },
        "to": {
          "Player": {
            "PlayerName": "林浩賢",
            "player_position": ""
          },
          "player_id": 6028,
          "leagueyearteamplayer_id": 7160,
          "leagueyearteam_id": 239,
          "clubplayer_id": null,
          "player_jersey": null
        }
      }
    },
    {
      "teamplayer_home_id": 0,
      "teamplayer_home_sub_id": 0,
      "teamplayer_guest_id": 7153,
      "teamplayer_guest_sub_id": 7148,
      "teamplayer_home": null,
      "teamplayer_home_sub": null,
      "teamplayer_guest": {
        "player_id": 6031,
        "club_id": 0,
        "PlayerName": "黃愷利",
        "player_position": ""
      },
      "teamplayer_guest_sub": {
        "player_id": 3768,
        "club_id": 0,
        "PlayerName": "馬家億",
        "player_position": ""
      },
      "EventType": "EXC",
      "side": "Guest",
      "min": 43,
      "minExtra": 0,
      "EXCPlayer": {
        "side": "Guest",
        "from": {
          "Player": {
            "PlayerName": "黃愷利",
            "player_position": ""
          },
          "player_id": 6031,
          "leagueyearteamplayer_id": 7153,
          "leagueyearteam_id": 239,
          "clubplayer_id": null,
          "player_jersey": null
        },
        "to": {
          "Player": {
            "PlayerName": "馬家億",
            "player_position": ""
          },
          "player_id": 3768,
          "leagueyearteamplayer_id": 7148,
          "leagueyearteam_id": 239,
          "clubplayer_id": null,
          "player_jersey": null
        }
      }
    },
    {
      "teamplayer_home_id": 0,
      "teamplayer_home_sub_id": 0,
      "teamplayer_guest_id": 7149,
      "teamplayer_guest_sub_id": 7152,
      "teamplayer_home": null,
      "teamplayer_home_sub": null,
      "teamplayer_guest": {
        "player_id": 6029,
        "club_id": 0,
        "PlayerName": "馬浩斌",
        "player_position": ""
      },
      "teamplayer_guest_sub": {
        "player_id": 6032,
        "club_id": 0,
        "PlayerName": "麥子豐",
        "player_position": ""
      },
      "EventType": "EXC",
      "side": "Guest",
      "min": 46,
      "minExtra": 0,
      "EXCPlayer": {
        "side": "Guest",
        "from": {
          "Player": {
            "PlayerName": "馬浩斌",
            "player_position": ""
          },
          "player_id": 6029,
          "leagueyearteamplayer_id": 7149,
          "leagueyearteam_id": 239,
          "clubplayer_id": null,
          "player_jersey": null
        },
        "to": {
          "Player": {
            "PlayerName": "麥子豐",
            "player_position": ""
          },
          "player_id": 6032,
          "leagueyearteamplayer_id": 7152,
          "leagueyearteam_id": 239,
          "clubplayer_id": null,
          "player_jersey": null
        }
      }
    }
  ]
}